{
  "timestamp": "2025-12-10T21:15:58.992567",
  "duration_seconds": 300,
  "start_time": "2025-12-10T16:10:58.573505",
  "end_time": "2025-12-10T16:15:58.573505",
  "metrics": {
    "hp_p50_latency": [],
    "hp_p95_latency": [],
    "hp_p99_latency": [],
    "request_rate": [],
    "sla_violation_rate": [],
    "drcio_hp_weight": [],
    "drcio_lp_weight": [],
    "drcio_adjustments": [],
    "cpu_usage": [
      {
        "metric": {
          "pod": "drcio-controller-fdzz9"
        },
        "values": [
          [
            1765401058.574,
            "0.0063920894587142455"
          ],
          [
            1765401063.574,
            "0.005812359835738152"
          ],
          [
            1765401068.574,
            "0.00571965712261157"
          ],
          [
            1765401073.574,
            "0.005802353345668608"
          ],
          [
            1765401078.574,
            "0.0056377771129902995"
          ],
          [
            1765401083.574,
            "0.0055653845270018125"
          ],
          [
            1765401088.574,
            "0.005514428402763267"
          ],
          [
            1765401093.574,
            "0.005514428402763267"
          ],
          [
            1765401098.574,
            "0.005011945787391713"
          ],
          [
            1765401103.574,
            "0.005501771329588484"
          ],
          [
            1765401108.574,
            "0.00526469825713953"
          ],
          [
            1765401113.574,
            "0.00560858437547607"
          ],
          [
            1765401118.574,
            "0.005044751422403406"
          ],
          [
            1765401123.574,
            "0.005129210132105454"
          ],
          [
            1765401128.574,
            "0.005001788794691993"
          ],
          [
            1765401133.574,
            "0.004998482593368738"
          ],
          [
            1765401138.574,
            "0.0051359159190172195"
          ],
          [
            1765401143.574,
            "0.005420394394074849"
          ],
          [
            1765401148.574,
            "0.005776382993614651"
          ],
          [
            1765401153.574,
            "0.005745847137073325"
          ],
          [
            1765401158.574,
            "0.0058543297455569444"
          ],
          [
            1765401163.574,
            "0.0054201077786842945"
          ],
          [
            1765401168.574,
            "0.00599673611143185"
          ],
          [
            1765401173.574,
            "0.006283045695848966"
          ],
          [
            1765401178.574,
            "0.0064356304193259346"
          ],
          [
            1765401183.574,
            "0.006430104248015667"
          ],
          [
            1765401188.574,
            "0.005914037585875956"
          ],
          [
            1765401193.574,
            "0.0061484372111712884"
          ],
          [
            1765401198.574,
            "0.005863190019180956"
          ],
          [
            1765401203.574,
            "0.0059890193300535365"
          ],
          [
            1765401208.574,
            "0.005099811483116158"
          ],
          [
            1765401213.574,
            "0.006160405983895877"
          ],
          [
            1765401218.574,
            "0.006160405983895877"
          ],
          [
            1765401223.574,
            "0.006160405983895877"
          ],
          [
            1765401228.574,
            "0.005658141110256891"
          ],
          [
            1765401233.574,
            "0.005582713835898298"
          ],
          [
            1765401238.574,
            "0.005761665000530982"
          ],
          [
            1765401243.574,
            "0.005838235245290486"
          ],
          [
            1765401248.574,
            "0.005838235245290486"
          ],
          [
            1765401253.574,
            "0.005309624959821476"
          ],
          [
            1765401258.574,
            "0.005259170266171549"
          ],
          [
            1765401263.574,
            "0.005259170266171549"
          ],
          [
            1765401268.574,
            "0.005259170266171549"
          ],
          [
            1765401273.574,
            "0.005850347794669112"
          ],
          [
            1765401278.574,
            "0.005850347794669112"
          ],
          [
            1765401283.574,
            "0.005850347794669112"
          ],
          [
            1765401288.574,
            "0.005445536232837086"
          ],
          [
            1765401293.574,
            "0.005981025467426931"
          ],
          [
            1765401298.574,
            "0.005981025467426931"
          ],
          [
            1765401303.574,
            "0.006561338982402329"
          ],
          [
            1765401308.574,
            "0.00650922924975352"
          ],
          [
            1765401313.574,
            "0.006100296966033062"
          ],
          [
            1765401318.574,
            "0.005836338647699673"
          ],
          [
            1765401323.574,
            "0.005836338647699673"
          ],
          [
            1765401328.574,
            "0.005912045509174621"
          ],
          [
            1765401333.574,
            "0.0052245654581897305"
          ],
          [
            1765401338.574,
            "0.005716874592729432"
          ],
          [
            1765401343.574,
            "0.005593817843749274"
          ],
          [
            1765401348.574,
            "0.005523649500828393"
          ],
          [
            1765401353.574,
            "0.005453077202890023"
          ],
          [
            1765401358.574,
            "0.005452411402151722"
          ]
        ]
      },
      {
        "metric": {
          "pod": "gnn-service-566dd5669f-jkql7"
        },
        "values": [
          [
            1765401058.574,
            "0.3483549908178407"
          ],
          [
            1765401063.574,
            "0.3353667364301133"
          ],
          [
            1765401068.574,
            "0.36718292251538076"
          ],
          [
            1765401073.574,
            "0.3369055775533262"
          ],
          [
            1765401078.574,
            "0.33782371359698904"
          ],
          [
            1765401083.574,
            "0.323801140817942"
          ],
          [
            1765401088.574,
            "0.35329337296632557"
          ],
          [
            1765401093.574,
            "0.35329337296632557"
          ],
          [
            1765401098.574,
            "0.3145863990277915"
          ],
          [
            1765401103.574,
            "0.2813292648442754"
          ],
          [
            1765401108.574,
            "0.26658239796616434"
          ],
          [
            1765401113.574,
            "0.29323790774011416"
          ],
          [
            1765401118.574,
            "0.3201046838675954"
          ],
          [
            1765401123.574,
            "0.32084019328646474"
          ],
          [
            1765401128.574,
            "0.31567071052883944"
          ],
          [
            1765401133.574,
            "0.3354611170374387"
          ],
          [
            1765401138.574,
            "0.2958190243684576"
          ],
          [
            1765401143.574,
            "0.31052583699154385"
          ],
          [
            1765401148.574,
            "0.3340530814269246"
          ],
          [
            1765401153.574,
            "0.29091235013568945"
          ],
          [
            1765401158.574,
            "0.29043829887381806"
          ],
          [
            1765401163.574,
            "0.33072493169625194"
          ],
          [
            1765401168.574,
            "0.3055636820595513"
          ],
          [
            1765401173.574,
            "0.3633561395348537"
          ],
          [
            1765401178.574,
            "0.3437449640472007"
          ],
          [
            1765401183.574,
            "0.3170768733325358"
          ],
          [
            1765401188.574,
            "0.2895818819992579"
          ],
          [
            1765401193.574,
            "0.27203012734978155"
          ],
          [
            1765401198.574,
            "0.2821076381669102"
          ],
          [
            1765401203.574,
            "0.2397249788873188"
          ],
          [
            1765401208.574,
            "0.26164027248712474"
          ],
          [
            1765401213.574,
            "0.22999379100214531"
          ],
          [
            1765401218.574,
            "0.20953460844258404"
          ],
          [
            1765401223.574,
            "0.16501037679967362"
          ],
          [
            1765401228.574,
            "0.12958467215965233"
          ],
          [
            1765401233.574,
            "0.14948606511859625"
          ],
          [
            1765401238.574,
            "0.20070879522943716"
          ],
          [
            1765401243.574,
            "0.23743706811285364"
          ],
          [
            1765401248.574,
            "0.29653046985922105"
          ],
          [
            1765401253.574,
            "0.30891024595023553"
          ],
          [
            1765401258.574,
            "0.32941900595152784"
          ],
          [
            1765401263.574,
            "0.3048050259820914"
          ],
          [
            1765401268.574,
            "0.37062957878525327"
          ],
          [
            1765401273.574,
            "0.3799403003026095"
          ],
          [
            1765401278.574,
            "0.3799403003026095"
          ],
          [
            1765401283.574,
            "0.4109885254766228"
          ],
          [
            1765401288.574,
            "0.4109885254766228"
          ],
          [
            1765401293.574,
            "0.4109885254766228"
          ],
          [
            1765401298.574,
            "0.39530431405048627"
          ],
          [
            1765401303.574,
            "0.3771709122358581"
          ],
          [
            1765401308.574,
            "0.31772331794896425"
          ],
          [
            1765401313.574,
            "0.3294432505542425"
          ],
          [
            1765401318.574,
            "0.26657612442757783"
          ],
          [
            1765401323.574,
            "0.2493576993986915"
          ],
          [
            1765401328.574,
            "0.2306793083565958"
          ],
          [
            1765401333.574,
            "0.15283484116733093"
          ],
          [
            1765401338.574,
            "0.22809883431862948"
          ],
          [
            1765401343.574,
            "0.21461341850831045"
          ],
          [
            1765401348.574,
            "0.2273573265508052"
          ],
          [
            1765401353.574,
            "0.26655808530682273"
          ],
          [
            1765401358.574,
            "0.2871939945180656"
          ]
        ]
      },
      {
        "metric": {
          "pod": "gnn-service-566dd5669f-ld4mn"
        },
        "values": [
          [
            1765401058.574,
            "0.3512218668547131"
          ],
          [
            1765401063.574,
            "0.32500867228297947"
          ],
          [
            1765401068.574,
            "0.3563457046406491"
          ],
          [
            1765401073.574,
            "0.3536432049144343"
          ],
          [
            1765401078.574,
            "0.3682801028639682"
          ],
          [
            1765401083.574,
            "0.3580133057569188"
          ],
          [
            1765401088.574,
            "0.3786078347030807"
          ],
          [
            1765401093.574,
            "0.3524610403113961"
          ],
          [
            1765401098.574,
            "0.30221092995389476"
          ],
          [
            1765401103.574,
            "0.28713957523005645"
          ],
          [
            1765401108.574,
            "0.28489783656348244"
          ],
          [
            1765401113.574,
            "0.2872853397654116"
          ],
          [
            1765401118.574,
            "0.29739608332645984"
          ],
          [
            1765401123.574,
            "0.303976452970911"
          ],
          [
            1765401128.574,
            "0.2969894662318294"
          ],
          [
            1765401133.574,
            "0.2442389606311977"
          ],
          [
            1765401138.574,
            "0.28126743595178216"
          ],
          [
            1765401143.574,
            "0.2958871437208485"
          ],
          [
            1765401148.574,
            "0.3032711570787999"
          ],
          [
            1765401153.574,
            "0.34749911929339566"
          ],
          [
            1765401158.574,
            "0.35831516414432496"
          ],
          [
            1765401163.574,
            "0.2985440757145815"
          ],
          [
            1765401168.574,
            "0.29877395511980875"
          ],
          [
            1765401173.574,
            "0.36451299399422554"
          ],
          [
            1765401178.574,
            "0.36451299399422554"
          ],
          [
            1765401183.574,
            "0.33132086181843123"
          ],
          [
            1765401188.574,
            "0.33132086181843123"
          ],
          [
            1765401193.574,
            "0.29332109786062655"
          ],
          [
            1765401198.574,
            "0.26079975914314185"
          ],
          [
            1765401203.574,
            "0.26641773808933916"
          ],
          [
            1765401208.574,
            "0.23610354523082677"
          ],
          [
            1765401213.574,
            "0.1548735535220909"
          ],
          [
            1765401218.574,
            "0.17107592447026834"
          ],
          [
            1765401223.574,
            "0.17701857219908024"
          ],
          [
            1765401228.574,
            "0.2045315163573455"
          ],
          [
            1765401233.574,
            "0.2181941665973358"
          ],
          [
            1765401238.574,
            "0.24025807253111808"
          ],
          [
            1765401243.574,
            "0.30054926167299634"
          ],
          [
            1765401248.574,
            "0.3138107505384131"
          ],
          [
            1765401253.574,
            "0.29727013727534946"
          ],
          [
            1765401258.574,
            "0.30833004735820846"
          ],
          [
            1765401263.574,
            "0.3269391072472665"
          ],
          [
            1765401268.574,
            "0.3269391072472665"
          ],
          [
            1765401273.574,
            "0.2905203814428654"
          ],
          [
            1765401278.574,
            "0.2871521686621703"
          ],
          [
            1765401283.574,
            "0.255012651773934"
          ],
          [
            1765401288.574,
            "0.24069392813472357"
          ],
          [
            1765401293.574,
            "0.20147865379827148"
          ],
          [
            1765401298.574,
            "0.15565967692415283"
          ],
          [
            1765401303.574,
            "0.18757380722692873"
          ],
          [
            1765401308.574,
            "0.23265793185601097"
          ],
          [
            1765401313.574,
            "0.24786970397264188"
          ],
          [
            1765401318.574,
            "0.3570463435185291"
          ],
          [
            1765401323.574,
            "0.3783347356927747"
          ],
          [
            1765401328.574,
            "0.4165454065423452"
          ],
          [
            1765401333.574,
            "0.4426663285377893"
          ],
          [
            1765401338.574,
            "0.46153100050598017"
          ],
          [
            1765401343.574,
            "0.427384775334397"
          ],
          [
            1765401348.574,
            "0.4924116053573076"
          ],
          [
            1765401353.574,
            "0.46411383675140894"
          ],
          [
            1765401358.574,
            "0.45148911957233867"
          ]
        ]
      }
    ],
    "memory_usage": [
      {
        "metric": {
          "pod": "drcio-controller-fdzz9"
        },
        "values": [
          [
            1765401058.574,
            "122753024"
          ],
          [
            1765401063.574,
            "122753024"
          ],
          [
            1765401068.574,
            "122753024"
          ],
          [
            1765401073.574,
            "122753024"
          ],
          [
            1765401078.574,
            "122753024"
          ],
          [
            1765401083.574,
            "122753024"
          ],
          [
            1765401088.574,
            "122753024"
          ],
          [
            1765401093.574,
            "122753024"
          ],
          [
            1765401098.574,
            "122753024"
          ],
          [
            1765401103.574,
            "122753024"
          ],
          [
            1765401108.574,
            "122753024"
          ],
          [
            1765401113.574,
            "122753024"
          ],
          [
            1765401118.574,
            "122753024"
          ],
          [
            1765401123.574,
            "122753024"
          ],
          [
            1765401128.574,
            "122753024"
          ],
          [
            1765401133.574,
            "122753024"
          ],
          [
            1765401138.574,
            "122753024"
          ],
          [
            1765401143.574,
            "122757120"
          ],
          [
            1765401148.574,
            "122757120"
          ],
          [
            1765401153.574,
            "122753024"
          ],
          [
            1765401158.574,
            "122753024"
          ],
          [
            1765401163.574,
            "122753024"
          ],
          [
            1765401168.574,
            "122753024"
          ],
          [
            1765401173.574,
            "122753024"
          ],
          [
            1765401178.574,
            "122765312"
          ],
          [
            1765401183.574,
            "122765312"
          ],
          [
            1765401188.574,
            "122765312"
          ],
          [
            1765401193.574,
            "122761216"
          ],
          [
            1765401198.574,
            "122761216"
          ],
          [
            1765401203.574,
            "122761216"
          ],
          [
            1765401208.574,
            "122761216"
          ],
          [
            1765401213.574,
            "122753024"
          ],
          [
            1765401218.574,
            "122753024"
          ],
          [
            1765401223.574,
            "122753024"
          ],
          [
            1765401228.574,
            "122753024"
          ],
          [
            1765401233.574,
            "122753024"
          ],
          [
            1765401238.574,
            "122753024"
          ],
          [
            1765401243.574,
            "122761216"
          ],
          [
            1765401248.574,
            "122761216"
          ],
          [
            1765401253.574,
            "122761216"
          ],
          [
            1765401258.574,
            "122761216"
          ],
          [
            1765401263.574,
            "122761216"
          ],
          [
            1765401268.574,
            "122761216"
          ],
          [
            1765401273.574,
            "122761216"
          ],
          [
            1765401278.574,
            "122761216"
          ],
          [
            1765401283.574,
            "122761216"
          ],
          [
            1765401288.574,
            "122761216"
          ],
          [
            1765401293.574,
            "122761216"
          ],
          [
            1765401298.574,
            "122761216"
          ],
          [
            1765401303.574,
            "122761216"
          ],
          [
            1765401308.574,
            "122761216"
          ],
          [
            1765401313.574,
            "122761216"
          ],
          [
            1765401318.574,
            "122761216"
          ],
          [
            1765401323.574,
            "122761216"
          ],
          [
            1765401328.574,
            "122761216"
          ],
          [
            1765401333.574,
            "122761216"
          ],
          [
            1765401338.574,
            "122761216"
          ],
          [
            1765401343.574,
            "122761216"
          ],
          [
            1765401348.574,
            "122761216"
          ],
          [
            1765401353.574,
            "122761216"
          ],
          [
            1765401358.574,
            "122761216"
          ]
        ]
      },
      {
        "metric": {
          "pod": "gnn-service-566dd5669f-jkql7"
        },
        "values": [
          [
            1765401058.574,
            "199507968"
          ],
          [
            1765401063.574,
            "199507968"
          ],
          [
            1765401068.574,
            "199507968"
          ],
          [
            1765401073.574,
            "199786496"
          ],
          [
            1765401078.574,
            "199827456"
          ],
          [
            1765401083.574,
            "199827456"
          ],
          [
            1765401088.574,
            "182915072"
          ],
          [
            1765401093.574,
            "184590336"
          ],
          [
            1765401098.574,
            "89759744"
          ],
          [
            1765401103.574,
            "89759744"
          ],
          [
            1765401108.574,
            "89759744"
          ],
          [
            1765401113.574,
            "187576320"
          ],
          [
            1765401118.574,
            "199516160"
          ],
          [
            1765401123.574,
            "199389184"
          ],
          [
            1765401128.574,
            "199389184"
          ],
          [
            1765401133.574,
            "200212480"
          ],
          [
            1765401138.574,
            "200212480"
          ],
          [
            1765401143.574,
            "200212480"
          ],
          [
            1765401148.574,
            "200261632"
          ],
          [
            1765401153.574,
            "200392704"
          ],
          [
            1765401158.574,
            "200392704"
          ],
          [
            1765401163.574,
            "200749056"
          ],
          [
            1765401168.574,
            "202280960"
          ],
          [
            1765401173.574,
            "202002432"
          ],
          [
            1765401178.574,
            "202002432"
          ],
          [
            1765401183.574,
            "204513280"
          ],
          [
            1765401188.574,
            "90566656"
          ],
          [
            1765401193.574,
            "90566656"
          ],
          [
            1765401198.574,
            "90566656"
          ],
          [
            1765401203.574,
            "178438144"
          ],
          [
            1765401208.574,
            "178438144"
          ],
          [
            1765401213.574,
            "178438144"
          ],
          [
            1765401218.574,
            "178438144"
          ],
          [
            1765401223.574,
            "198287360"
          ],
          [
            1765401228.574,
            "198287360"
          ],
          [
            1765401233.574,
            "198287360"
          ],
          [
            1765401238.574,
            "198483968"
          ],
          [
            1765401243.574,
            "198852608"
          ],
          [
            1765401248.574,
            "199057408"
          ],
          [
            1765401253.574,
            "199057408"
          ],
          [
            1765401258.574,
            "199323648"
          ],
          [
            1765401263.574,
            "199323648"
          ],
          [
            1765401268.574,
            "199569408"
          ],
          [
            1765401273.574,
            "199589888"
          ],
          [
            1765401278.574,
            "199589888"
          ],
          [
            1765401283.574,
            "157659136"
          ],
          [
            1765401288.574,
            "157659136"
          ],
          [
            1765401293.574,
            "157659136"
          ],
          [
            1765401298.574,
            "136957952"
          ],
          [
            1765401303.574,
            "136957952"
          ],
          [
            1765401308.574,
            "61976576"
          ],
          [
            1765401313.574,
            "61976576"
          ],
          [
            1765401318.574,
            "91549696"
          ],
          [
            1765401323.574,
            "91549696"
          ],
          [
            1765401328.574,
            "187453440"
          ],
          [
            1765401333.574,
            "187453440"
          ],
          [
            1765401338.574,
            "198946816"
          ],
          [
            1765401343.574,
            "198946816"
          ],
          [
            1765401348.574,
            "198946816"
          ],
          [
            1765401353.574,
            "199049216"
          ],
          [
            1765401358.574,
            "199139328"
          ]
        ]
      },
      {
        "metric": {
          "pod": "gnn-service-566dd5669f-ld4mn"
        },
        "values": [
          [
            1765401058.574,
            "200257536"
          ],
          [
            1765401063.574,
            "200269824"
          ],
          [
            1765401068.574,
            "200269824"
          ],
          [
            1765401073.574,
            "200237056"
          ],
          [
            1765401078.574,
            "200237056"
          ],
          [
            1765401083.574,
            "191852544"
          ],
          [
            1765401088.574,
            "183496704"
          ],
          [
            1765401093.574,
            "186114048"
          ],
          [
            1765401098.574,
            "94679040"
          ],
          [
            1765401103.574,
            "175124480"
          ],
          [
            1765401108.574,
            "175124480"
          ],
          [
            1765401113.574,
            "187109376"
          ],
          [
            1765401118.574,
            "187109376"
          ],
          [
            1765401123.574,
            "199614464"
          ],
          [
            1765401128.574,
            "199614464"
          ],
          [
            1765401133.574,
            "199700480"
          ],
          [
            1765401138.574,
            "200101888"
          ],
          [
            1765401143.574,
            "200101888"
          ],
          [
            1765401148.574,
            "200126464"
          ],
          [
            1765401153.574,
            "200286208"
          ],
          [
            1765401158.574,
            "200286208"
          ],
          [
            1765401163.574,
            "200286208"
          ],
          [
            1765401168.574,
            "200343552"
          ],
          [
            1765401173.574,
            "200331264"
          ],
          [
            1765401178.574,
            "200331264"
          ],
          [
            1765401183.574,
            "202981376"
          ],
          [
            1765401188.574,
            "103170048"
          ],
          [
            1765401193.574,
            "103170048"
          ],
          [
            1765401198.574,
            "91664384"
          ],
          [
            1765401203.574,
            "177242112"
          ],
          [
            1765401208.574,
            "177242112"
          ],
          [
            1765401213.574,
            "185475072"
          ],
          [
            1765401218.574,
            "193953792"
          ],
          [
            1765401223.574,
            "193953792"
          ],
          [
            1765401228.574,
            "196382720"
          ],
          [
            1765401233.574,
            "199249920"
          ],
          [
            1765401238.574,
            "199553024"
          ],
          [
            1765401243.574,
            "199700480"
          ],
          [
            1765401248.574,
            "199700480"
          ],
          [
            1765401253.574,
            "199700480"
          ],
          [
            1765401258.574,
            "199204864"
          ],
          [
            1765401263.574,
            "199204864"
          ],
          [
            1765401268.574,
            "199204864"
          ],
          [
            1765401273.574,
            "169959424"
          ],
          [
            1765401278.574,
            "70737920"
          ],
          [
            1765401283.574,
            "91254784"
          ],
          [
            1765401288.574,
            "91254784"
          ],
          [
            1765401293.574,
            "91254784"
          ],
          [
            1765401298.574,
            "186753024"
          ],
          [
            1765401303.574,
            "198381568"
          ],
          [
            1765401308.574,
            "198909952"
          ],
          [
            1765401313.574,
            "198909952"
          ],
          [
            1765401318.574,
            "200519680"
          ],
          [
            1765401323.574,
            "200519680"
          ],
          [
            1765401328.574,
            "199823360"
          ],
          [
            1765401333.574,
            "199847936"
          ],
          [
            1765401338.574,
            "199847936"
          ],
          [
            1765401343.574,
            "199892992"
          ],
          [
            1765401348.574,
            "200015872"
          ],
          [
            1765401353.574,
            "200085504"
          ],
          [
            1765401358.574,
            "200085504"
          ]
        ]
      }
    ],
    "summary": {}
  }
}